osdentalMobileLibrary/__init__.py
osdentalMobileLibrary/Database/Connection.py
osdentalMobileLibrary/Database/__init__.py
osdentalMobileLibrary/Decorators/AuditLogMobile.py
osdentalMobileLibrary/Decorators/Grpc.py
osdentalMobileLibrary/Decorators/Retry.py
osdentalMobileLibrary/Decorators/__init__.py
osdentalMobileLibrary/Exception/ControlledException.py
osdentalMobileLibrary/Exception/__init__.py
osdentalMobileLibrary/ExternalHttp/Client.py
osdentalMobileLibrary/ExternalHttp/__init__.py
osdentalMobileLibrary/Grpc/__init__.py
osdentalMobileLibrary/Grpc/Base/GrpcClientBase.py
osdentalMobileLibrary/Grpc/Base/__init__.py
osdentalMobileLibrary/Grpc/Client/AuthClient.py
osdentalMobileLibrary/Grpc/Client/__init__.py
osdentalMobileLibrary/Grpc/Generated/AuthProto_pb2.py
osdentalMobileLibrary/Grpc/Generated/AuthProto_pb2_grpc.py
osdentalMobileLibrary/Grpc/Generated/Common_pb2.py
osdentalMobileLibrary/Grpc/Generated/Common_pb2_grpc.py
osdentalMobileLibrary/Grpc/Generated/__init__.py
osdentalMobileLibrary/Models/Catalog.py
osdentalMobileLibrary/Models/Response.py
osdentalMobileLibrary/Models/__init__.py
osdentalMobileLibrary/ServicesBus/ServicesBus.py
osdentalMobileLibrary/ServicesBus/TaskQueue.py
osdentalMobileLibrary/ServicesBus/__init__.py
osdentalMobileLibrary/Shared/Logger.py
osdentalMobileLibrary/Shared/__init__.py
osdentalMobileLibrary/Shared/Config/__init__.py
osdentalMobileLibrary/Shared/Enums/Code.py
osdentalMobileLibrary/Shared/Enums/Constant.py
osdentalMobileLibrary/Shared/Enums/FileType.py
osdentalMobileLibrary/Shared/Enums/Message.py
osdentalMobileLibrary/Shared/Enums/Profile.py
osdentalMobileLibrary/Shared/Enums/__init__.py
osdentalMobileLibrary/Shared/Utils/CaseConverter.py
osdentalMobileLibrary/Shared/Utils/CodeGenerator.py
osdentalMobileLibrary/Shared/Utils/DataUtils.py
osdentalMobileLibrary/Shared/Utils/DateUtils.py
osdentalMobileLibrary/Shared/Utils/TextProcessor.py
osdentalMobileLibrary/Shared/Utils/__init__.py
osdental_mb_library-0.2.8.dist-info/METADATA
osdental_mb_library-0.2.8.dist-info/WHEEL
osdental_mb_library-0.2.8.dist-info/top_level.txt
osdental_mb_library-0.2.8.dist-info/RECORD
