Metadata-Version: 2.4
Name: osdental-mb-library
Version: 0.2.8
Summary: Internal mobile library for OSDental
Author-email: aalvia <aalvia@osdental.ai>
License-Expression: MIT
Classifier: Programming Language :: Python :: 3
Classifier: Operating System :: OS Independent
Requires-Python: >=3.10
Requires-Dist: starlette
Requires-Dist: strawberry-graphql
Requires-Dist: python-json-logger
Requires-Dist: grpcio
Requires-Dist: grpcio-tools
Requires-Dist: uvicorn
Requires-Dist: azure-monitor-opentelemetry==1.8.1
